MANIFEST.in
README.md
setup.cfg
setup.py
petra_camera/__init__.py
petra_camera/default_config.xml
petra_camera/main_window.py
petra_camera/petra_camera.sh
petra_camera/version.py
petra_camera.egg-info/PKG-INFO
petra_camera.egg-info/SOURCES.txt
petra_camera.egg-info/dependency_links.txt
petra_camera.egg-info/entry_points.txt
petra_camera.egg-info/requires.txt
petra_camera.egg-info/top_level.txt
petra_camera/devices/__init__.py
petra_camera/devices/axiscamera.py
petra_camera/devices/base_camera.py
petra_camera/devices/dalsa.py
petra_camera/devices/datasource2d.py
petra_camera/devices/dummy.py
petra_camera/devices/lambda.py
petra_camera/devices/lmscreen.py
petra_camera/devices/petrastatus.py
petra_camera/devices/screen_motor.py
petra_camera/devices/tangovimba.py
petra_camera/external/__init__.py
petra_camera/external/histogramWidget.py
petra_camera/external/pyqtgraph_0_12.py
petra_camera/gui/AboutDialog_ui.py
petra_camera/gui/CameraSettings_ui.py
petra_camera/gui/CameraWidget_ui.py
petra_camera/gui/FrameViewer_ui.py
petra_camera/gui/ImportCameras_ui.py
petra_camera/gui/LogWidget_ui.py
petra_camera/gui/MainWindow_ui.py
petra_camera/gui/Marker_ui.py
petra_camera/gui/MarkersROIs_ui.py
petra_camera/gui/PeakSearch_ui.py
petra_camera/gui/PositionControl_ui.py
petra_camera/gui/ProjectionWidget_ui.py
petra_camera/gui/ROI_ui.py
petra_camera/gui/SettingsDialog_ui.py
petra_camera/gui/SettingsWidget_ui.py
petra_camera/gui/__init__.py
petra_camera/gui/batch_ui.py
petra_camera/gui/icons_rc.py
petra_camera/roisrv/__init__.py
petra_camera/roisrv/roiserver.py
petra_camera/utils/__init__.py
petra_camera/utils/errors.py
petra_camera/utils/functions.py
petra_camera/utils/gui_elements.py
petra_camera/utils/guilogger.py
petra_camera/utils/propagating_thread.py
petra_camera/utils/tango_utils.py
petra_camera/utils/xmlsettings.py
petra_camera/widgets/__init__.py
petra_camera/widgets/about_dialog.py
petra_camera/widgets/base_widget.py
petra_camera/widgets/batch_progress.py
petra_camera/widgets/camera_settings.py
petra_camera/widgets/camera_widget.py
petra_camera/widgets/frame_viewer.py
petra_camera/widgets/general_settings.py
petra_camera/widgets/image_view.py
petra_camera/widgets/import_cameras.py
