Metadata-Version: 2.1
Name: petra-camera
Version: 1.1.0
Summary: Simple viewer for cameras, used at PETRA III source
Home-page: UNKNOWN
Author: Yury Matveyev
Author-email: yury.matveev@desy.de
License: GPLv3
Platform: UNKNOWN
Classifier: License :: OSI Approved :: GNU General Public License v3 (GPLv3)
Classifier: Programming Language :: Python
Classifier: Programming Language :: Python :: 3
Classifier: Programming Language :: Python :: 3.7
Classifier: Programming Language :: Python :: Implementation :: CPython
Classifier: Development Status :: 5 - Production/Stable
Requires-Python: >=3.7
Provides-Extra: LAMBDA
Provides-Extra: PEAK
